bitstring.py
thread_bitstring-3.1.5.dist-info/DESCRIPTION.rst
thread_bitstring-3.1.5.dist-info/METADATA
thread_bitstring-3.1.5.dist-info/RECORD
thread_bitstring-3.1.5.dist-info/WHEEL
thread_bitstring-3.1.5.dist-info/metadata.json
thread_bitstring-3.1.5.dist-info/top_level.txt
