Metadata-Version: 2.0
Name: thread-bitstring
Version: 3.1.5
Summary: Simple construction, analysis and modification of binary data.
Home-page: https://github.com/scott-griffiths/bitstring
Author: Scott Griffiths
Author-email: dr.scottgriffiths@gmail.com
License: The MIT License: http://www.opensource.org/licenses/mit-license.php
Download-URL: https://pypi.python.org/pypi/bitstring/
Platform: all
Classifier: Development Status :: 5 - Production/Stable
Classifier: Intended Audience :: Developers
Classifier: Operating System :: OS Independent
Classifier: License :: OSI Approved :: MIT License
Classifier: Programming Language :: Python :: 2.6
Classifier: Programming Language :: Python :: 2.7
Classifier: Programming Language :: Python :: 3
Classifier: Programming Language :: Python :: 3.0
Classifier: Programming Language :: Python :: 3.1
Classifier: Programming Language :: Python :: 3.2
Classifier: Programming Language :: Python :: 3.3
Classifier: Programming Language :: Python :: 3.4
Classifier: Programming Language :: Python :: 3.5
Classifier: Topic :: Software Development :: Libraries :: Python Modules
